batch_processing_discovery/__init__.py
batch_processing_discovery/batch_characteristics.py
batch_processing_discovery/config.py
batch_processing_discovery/discovery.py
batch_processing_discovery/features_table.py
batch_processing_discovery/rules.py
batch_processing_discovery-0.4.4.dist-info/LICENSE
batch_processing_discovery-0.4.4.dist-info/METADATA
batch_processing_discovery-0.4.4.dist-info/WHEEL
batch_processing_discovery-0.4.4.dist-info/RECORD
