Metadata-Version: 2.1
Name: batch-processing-discovery
Version: 0.4.4
Summary: Python algorithm to discover, from an event log, activity instances that are executed in a batch.
Author: David Chapela de la Campa
Author-email: david.chapela.delacampa@gmail.com
Requires-Python: >=3.9,<3.12
Classifier: Programming Language :: Python :: 3
Classifier: Programming Language :: Python :: 3.9
Classifier: Programming Language :: Python :: 3.10
Classifier: Programming Language :: Python :: 3.11
Requires-Dist: pandas (>=2.0.2,<3.0.0)
Requires-Dist: wittgenstein (>=0.3.4,<0.4.0)
